[{"citycode":"0593","adcode":"350902","name":"\u8549\u57ce\u533a","level":"district","center_N":26.659253,"center_J":119.527225,"center_lng":119.527225,"center_lat":26.659253},{"citycode":"0593","adcode":"350921","name":"\u971e\u6d66\u53bf","level":"district","center_N":26.882068,"center_J":120.005214,"center_lng":120.005214,"center_lat":26.882068},{"citycode":"0593","adcode":"350922","name":"\u53e4\u7530\u53bf","level":"district","center_N":26.577491,"center_J":118.743156,"center_lng":118.743156,"center_lat":26.577491},{"citycode":"0593","adcode":"350923","name":"\u5c4f\u5357\u53bf","level":"district","center_N":26.910826,"center_J":118.987544,"center_lng":118.987544,"center_lat":26.910826},{"citycode":"0593","adcode":"350924","name":"\u5bff\u5b81\u53bf","level":"district","center_N":27.457798,"center_J":119.506733,"center_lng":119.506733,"center_lat":27.457798},{"citycode":"0593","adcode":"350925","name":"\u5468\u5b81\u53bf","level":"district","center_N":27.103106,"center_J":119.338239,"center_lng":119.338239,"center_lat":27.103106},{"citycode":"0593","adcode":"350926","name":"\u67d8\u8363\u53bf","level":"district","center_N":27.236163,"center_J":119.898226,"center_lng":119.898226,"center_lat":27.236163},{"citycode":"0593","adcode":"350981","name":"\u798f\u5b89\u5e02","level":"district","center_N":27.084246,"center_J":119.650798,"center_lng":119.650798,"center_lat":27.084246},{"citycode":"0593","adcode":"350982","name":"\u798f\u9f0e\u5e02","level":"district","center_N":27.318884,"center_J":120.219761,"center_lng":120.219761,"center_lat":27.318884}]