[{"citycode":"0762","adcode":"441602","name":"\u6e90\u57ce\u533a","level":"district","center_N":23.746255,"center_J":114.696828,"center_lng":114.696828,"center_lat":23.746255},{"citycode":"0762","adcode":"441621","name":"\u7d2b\u91d1\u53bf","level":"district","center_N":23.633744,"center_J":115.184383,"center_lng":115.184383,"center_lat":23.633744},{"citycode":"0762","adcode":"441622","name":"\u9f99\u5ddd\u53bf","level":"district","center_N":24.101174,"center_J":115.256415,"center_lng":115.256415,"center_lat":24.101174},{"citycode":"0762","adcode":"441623","name":"\u8fde\u5e73\u53bf","level":"district","center_N":24.364227,"center_J":114.495952,"center_lng":114.495952,"center_lat":24.364227},{"citycode":"0762","adcode":"441624","name":"\u548c\u5e73\u53bf","level":"district","center_N":24.44318,"center_J":114.941473,"center_lng":114.941473,"center_lat":24.44318},{"citycode":"0762","adcode":"441625","name":"\u4e1c\u6e90\u53bf","level":"district","center_N":23.789093,"center_J":114.742711,"center_lng":114.742711,"center_lat":23.789093}]