[{"citycode":"0312","adcode":"130626","name":"\u6768\u6751\u4e61","level":"street","center_N":0,"center_J":0,"center_lng":115.838204,"center_lat":39.145457},{"citycode":"0312","adcode":"130626","name":"\u5c0f\u6731\u5e84\u9547","level":"street","center_N":0,"center_J":0,"center_lng":115.917949,"center_lat":39.209868},{"citycode":"0312","adcode":"130626","name":"\u56fa\u57ce\u9547","level":"street","center_N":0,"center_J":0,"center_lng":115.723504,"center_lat":39.140313},{"citycode":"0312","adcode":"130626","name":"\u5929\u5bab\u5bfa\u4e61","level":"street","center_N":0,"center_J":0,"center_lng":115.898095,"center_lat":39.237134},{"citycode":"0312","adcode":"130626","name":"\u9ad8\u91cc\u4e61","level":"street","center_N":0,"center_J":0,"center_lng":115.689961,"center_lat":39.277963},{"citycode":"0312","adcode":"130626","name":"\u5f20\u5bb6\u5e84\u4e61","level":"street","center_N":0,"center_J":0,"center_lng":115.561408,"center_lat":39.210962},{"citycode":"0312","adcode":"130626","name":"\u4e1c\u843d\u5821\u4e61","level":"street","center_N":0,"center_J":0,"center_lng":115.766525,"center_lat":39.277294},{"citycode":"0312","adcode":"130626","name":"\u5c0f\u6731\u5e84\u4e61","level":"street","center_N":0,"center_J":0,"center_lng":115.9179,"center_lat":39.209871},{"citycode":"0312","adcode":"130626","name":"\u8d24\u5bd3\u9547","level":"street","center_N":0,"center_J":0,"center_lng":115.617001,"center_lat":39.178215},{"citycode":"0312","adcode":"130626","name":"\u5317\u6cb3\u9547","level":"street","center_N":0,"center_J":0,"center_lng":115.76011,"center_lat":39.213409},{"citycode":"0312","adcode":"130626","name":"\u5317\u7530\u4e61","level":"street","center_N":0,"center_J":0,"center_lng":115.862911,"center_lat":39.159741},{"citycode":"0312","adcode":"130626","name":"\u674e\u90c1\u5e84\u4e61","level":"street","center_N":0,"center_J":0,"center_lng":115.858961,"center_lat":39.238159},{"citycode":"0312","adcode":"130626","name":"\u5b9a\u5174\u9547","level":"street","center_N":0,"center_J":0,"center_lng":115.791183,"center_lat":39.266834},{"citycode":"0312","adcode":"130626","name":"\u59da\u6751\u4e61","level":"street","center_N":0,"center_J":0,"center_lng":115.545413,"center_lat":39.151663},{"citycode":"0312","adcode":"130626","name":"\u5317\u5357\u8521\u4e61","level":"street","center_N":0,"center_J":0,"center_lng":115.907935,"center_lat":39.129329},{"citycode":"0312","adcode":"130626","name":"\u8096\u6751\u4e61","level":"street","center_N":0,"center_J":0,"center_lng":115.703646,"center_lat":39.17358},{"citycode":"0312","adcode":"130626","name":"\u67f3\u5353\u4e61","level":"street","center_N":0,"center_J":0,"center_lng":115.771621,"center_lat":39.174269}]