[{"citycode":"0313","adcode":"130705","name":"\u5854\u513f\u6751\u4e61","level":"street","center_N":0,"center_J":0,"center_lng":114.889209,"center_lat":40.589293},{"citycode":"0313","adcode":"130705","name":"\u5e9e\u5bb6\u5821\u9547","level":"street","center_N":0,"center_J":0,"center_lng":115.408017,"center_lat":40.670141},{"citycode":"0313","adcode":"130705","name":"\u5de5\u4e1a\u8857\u8857\u9053","level":"street","center_N":0,"center_J":0,"center_lng":115.088914,"center_lat":40.601225},{"citycode":"0313","adcode":"130705","name":"\u5357\u5173\u8857\u8857\u9053","level":"street","center_N":0,"center_J":0,"center_lng":115.06369,"center_lat":40.599234},{"citycode":"0313","adcode":"130705","name":"\u6c5f\u5bb6\u5c6f\u4e61","level":"street","center_N":0,"center_J":0,"center_lng":114.954408,"center_lat":40.60654},{"citycode":"0313","adcode":"130705","name":"\u4faf\u5bb6\u5e99\u4e61","level":"street","center_N":0,"center_J":0,"center_lng":115.11618,"center_lat":40.592319},{"citycode":"0313","adcode":"130705","name":"\u674e\u5bb6\u5821\u4e61","level":"street","center_N":0,"center_J":0,"center_lng":115.397793,"center_lat":40.690649},{"citycode":"0313","adcode":"130705","name":"\u4e1c\u5347\u8857\u9053","level":"street","center_N":0,"center_J":0,"center_lng":115.090999,"center_lat":40.601388},{"citycode":"0313","adcode":"130705","name":"\u5efa\u56fd\u8857\u8857\u9053","level":"street","center_N":0,"center_J":0,"center_lng":115.096612,"center_lat":40.608248},{"citycode":"0313","adcode":"130705","name":"\u8d75\u5ddd\u9547","level":"street","center_N":0,"center_J":0,"center_lng":115.352347,"center_lat":40.682645},{"citycode":"0313","adcode":"130705","name":"\u6625\u5149\u4e61","level":"street","center_N":0,"center_J":0,"center_lng":115.044166,"center_lat":40.608758},{"citycode":"0313","adcode":"130705","name":"\u5d1e\u6751\u9547","level":"street","center_N":0,"center_J":0,"center_lng":115.01666,"center_lat":40.486824},{"citycode":"0313","adcode":"130705","name":"\u5357\u5173\u8857\u9053","level":"street","center_N":0,"center_J":0,"center_lng":115.059962,"center_lat":40.600644},{"citycode":"0313","adcode":"130705","name":"\u8d3e\u5bb6\u8425\u9547","level":"street","center_N":0,"center_J":0,"center_lng":115.217703,"center_lat":40.615873},{"citycode":"0313","adcode":"130705","name":"\u987e\u5bb6\u8425\u9547","level":"street","center_N":0,"center_J":0,"center_lng":115.14976,"center_lat":40.550739},{"citycode":"0313","adcode":"130705","name":"\u738b\u5bb6\u6e7e\u4e61","level":"street","center_N":0,"center_J":0,"center_lng":114.85049,"center_lat":40.265309},{"citycode":"0313","adcode":"130705","name":"\u6d0b\u6cb3\u5357\u9547","level":"street","center_N":0,"center_J":0,"center_lng":115.036576,"center_lat":40.573755},{"citycode":"0313","adcode":"130705","name":"\u6df1\u4e95\u9547","level":"street","center_N":0,"center_J":0,"center_lng":114.836508,"center_lat":40.403746},{"citycode":"0313","adcode":"130705","name":"\u5929\u6cf0\u5bfa\u8857\u9053","level":"street","center_N":0,"center_J":0,"center_lng":115.060197,"center_lat":40.610812},{"citycode":"0313","adcode":"130705","name":"\u7687\u57ce\u8857\u8857\u9053","level":"street","center_N":0,"center_J":0,"center_lng":115.057067,"center_lat":40.614914},{"citycode":"0313","adcode":"130705","name":"\u6cb3\u5b50\u897f\u4e61","level":"street","center_N":0,"center_J":0,"center_lng":115.025417,"center_lat":40.617488},{"citycode":"0313","adcode":"130705","name":"\u5927\u5317\u8857\u8857\u9053","level":"street","center_N":0,"center_J":0,"center_lng":115.063244,"center_lat":40.620516},{"citycode":"0313","adcode":"130705","name":"\u6797\u573a","level":"street","center_N":0,"center_J":0,"center_lng":115.073913,"center_lat":40.54031}]