[{"citycode":"0353","adcode":"140303","name":"\u8521\u6d3c\u8857\u9053","level":"street","center_N":0,"center_J":0,"center_lng":113.539242,"center_lat":37.871255},{"citycode":"0353","adcode":"140303","name":"\u5e73\u6f6d\u8857\u8857\u9053","level":"street","center_N":0,"center_J":0,"center_lng":113.562806,"center_lat":37.867009},{"citycode":"0353","adcode":"140303","name":"\u8d5b\u9c7c\u8857\u9053","level":"street","center_N":0,"center_J":0,"center_lng":113.512219,"center_lat":37.878407},{"citycode":"0353","adcode":"140303","name":"\u6c99\u576a\u8857\u9053","level":"street","center_N":0,"center_J":0,"center_lng":113.51494,"center_lat":37.894874},{"citycode":"0353","adcode":"140303","name":"\u6865\u5934\u8857\u9053","level":"street","center_N":0,"center_J":0,"center_lng":113.544829,"center_lat":37.874877}]