[{"citycode":"0358","adcode":"141129","name":"\u91d1\u7f57\u9547","level":"street","center_N":0,"center_J":0,"center_lng":111.12589,"center_lat":37.435845},{"citycode":"0358","adcode":"141129","name":"\u4e0b\u67a3\u6797\u4e61","level":"street","center_N":0,"center_J":0,"center_lng":111.093416,"center_lat":37.344435},{"citycode":"0358","adcode":"141129","name":"\u5f20\u5b50\u5c71\u4e61","level":"street","center_N":0,"center_J":0,"center_lng":111.133938,"center_lat":37.439356},{"citycode":"0358","adcode":"141129","name":"\u5b81\u4e61\u9547","level":"street","center_N":0,"center_J":0,"center_lng":111.185584,"center_lat":37.35306},{"citycode":"0358","adcode":"141129","name":"\u8f66\u9e23\u5cea\u4e61","level":"street","center_N":0,"center_J":0,"center_lng":111.22874,"center_lat":37.232188},{"citycode":"0358","adcode":"141129","name":"\u6696\u6cc9\u9547","level":"street","center_N":0,"center_J":0,"center_lng":110.998909,"center_lat":37.119693},{"citycode":"0358","adcode":"141129","name":"\u679d\u67ef\u9547","level":"street","center_N":0,"center_J":0,"center_lng":111.303219,"center_lat":37.293304},{"citycode":"0358","adcode":"141129","name":"\u6b66\u5bb6\u5e84\u9547","level":"street","center_N":0,"center_J":0,"center_lng":111.004397,"center_lat":37.247405}]