[{"citycode":"0471","adcode":"150122","name":"\u6c38\u5723\u57df\u4e61","level":"street","center_N":0,"center_J":0,"center_lng":111.46502,"center_lat":40.488762},{"citycode":"0471","adcode":"150122","name":"\u53cc\u6cb3\u9547","level":"street","center_N":0,"center_J":0,"center_lng":111.231629,"center_lat":40.270701},{"citycode":"0471","adcode":"150122","name":"\u65b0\u8425\u5b50\u9547","level":"street","center_N":0,"center_J":0,"center_lng":111.37599,"center_lat":40.247939},{"citycode":"0471","adcode":"150122","name":"\u4e94\u7533\u9547","level":"street","center_N":0,"center_J":0,"center_lng":111.148806,"center_lat":40.403149},{"citycode":"0471","adcode":"150122","name":"\u53e4\u57ce\u9547","level":"street","center_N":0,"center_J":0,"center_lng":111.352542,"center_lat":40.525956},{"citycode":"0471","adcode":"150122","name":"\u5357\u576a\u4e61","level":"street","center_N":0,"center_J":0,"center_lng":111.19801,"center_lat":40.27377},{"citycode":"0471","adcode":"150122","name":"\u4e2d\u6ee9\u4e61","level":"street","center_N":0,"center_J":0,"center_lng":111.155429,"center_lat":40.270741},{"citycode":"0471","adcode":"150122","name":"\u4f0d\u4ec0\u5bb6\u9547","level":"street","center_N":0,"center_J":0,"center_lng":111.322093,"center_lat":40.356751}]