[{"citycode":"0452","adcode":"230221","name":"\u9f99\u6c5f\u9547","level":"street","center_N":0,"center_J":0,"center_lng":123.184447,"center_lat":47.331913},{"citycode":"0452","adcode":"230221","name":"\u5341\u91cc\u755c\u7267\u573a","level":"street","center_N":0,"center_J":0,"center_lng":123.416934,"center_lat":47.366399},{"citycode":"0452","adcode":"230221","name":"\u534e\u6c11\u4e61","level":"street","center_N":0,"center_J":0,"center_lng":123.452672,"center_lat":47.13002},{"citycode":"0452","adcode":"230221","name":"\u4e03\u68f5\u6811\u9547","level":"street","center_N":0,"center_J":0,"center_lng":123.259265,"center_lat":47.529967},{"citycode":"0452","adcode":"230221","name":"\u54c8\u62c9\u6d77\u4e61","level":"street","center_N":0,"center_J":0,"center_lng":123.411599,"center_lat":47.437202},{"citycode":"0452","adcode":"230221","name":"\u9ed1\u5c97\u4e61","level":"street","center_N":0,"center_J":0,"center_lng":123.405479,"center_lat":47.247751},{"citycode":"0452","adcode":"230221","name":"\u6b63\u9633\u755c\u7267\u573a","level":"street","center_N":0,"center_J":0,"center_lng":123.338825,"center_lat":47.653856},{"citycode":"0452","adcode":"230221","name":"\u5c71\u6cc9\u9547","level":"street","center_N":0,"center_J":0,"center_lng":122.87338,"center_lat":47.239101},{"citycode":"0452","adcode":"230221","name":"\u5357\u71d5\u6751\u755c\u7267\u573a","level":"street","center_N":0,"center_J":0,"center_lng":122.541872,"center_lat":47.203049},{"citycode":"0452","adcode":"230221","name":"\u6d4e\u6c81\u6cb3\u4e61","level":"street","center_N":0,"center_J":0,"center_lng":122.704065,"center_lat":47.381938},{"citycode":"0452","adcode":"230221","name":"\u6c38\u53d1\u4e61","level":"street","center_N":0,"center_J":0,"center_lng":123.049417,"center_lat":47.159903},{"citycode":"0452","adcode":"230221","name":"\u666f\u661f\u9547","level":"street","center_N":0,"center_J":0,"center_lng":123.034329,"center_lat":47.081661},{"citycode":"0452","adcode":"230221","name":"\u7eff\u8272\u6d77\u6d0b\u6797\u573a","level":"street","center_N":0,"center_J":0,"center_lng":123.026455,"center_lat":46.976379},{"citycode":"0452","adcode":"230221","name":"\u534e\u6c11\u755c\u7267\u573a","level":"street","center_N":0,"center_J":0,"center_lng":123.425156,"center_lat":47.107997},{"citycode":"0452","adcode":"230221","name":"\u897f\u516d\u4e5d\u5927\u961f\u6797\u573a","level":"street","center_N":0,"center_J":0,"center_lng":122.792839,"center_lat":46.996447},{"citycode":"0452","adcode":"230221","name":"\u9f99\u5174\u9547","level":"street","center_N":0,"center_J":0,"center_lng":122.760418,"center_lat":47.4901},{"citycode":"0452","adcode":"230221","name":"\u5e7f\u539a\u4e61","level":"street","center_N":0,"center_J":0,"center_lng":123.392359,"center_lat":47.076351},{"citycode":"0452","adcode":"230221","name":"\u674f\u5c71\u4e61","level":"street","center_N":0,"center_J":0,"center_lng":122.967621,"center_lat":46.93913},{"citycode":"0452","adcode":"230221","name":"\u5317\u71d5\u755c\u7267\u573a","level":"street","center_N":0,"center_J":0,"center_lng":122.592583,"center_lat":47.234463},{"citycode":"0452","adcode":"230221","name":"\u6d4e\u6c81\u6cb3\u4e61\u7267\u573a","level":"street","center_N":0,"center_J":0,"center_lng":122.463423,"center_lat":47.31823},{"citycode":"0452","adcode":"230221","name":"\u9f99\u54c8\u9752\u5e74\u519c\u573a","level":"street","center_N":0,"center_J":0,"center_lng":123.331597,"center_lat":47.23948},{"citycode":"0452","adcode":"230221","name":"\u5934\u7ad9\u9547","level":"street","center_N":0,"center_J":0,"center_lng":123.255565,"center_lat":46.96682},{"citycode":"0452","adcode":"230221","name":"\u5174\u9686\u5ddd\u4e61","level":"street","center_N":0,"center_J":0,"center_lng":122.849758,"center_lat":47.152572},{"citycode":"0452","adcode":"230221","name":"\u9ed1\u5c97\u519c\u7267\u573a","level":"street","center_N":0,"center_J":0,"center_lng":123.472535,"center_lat":47.249349},{"citycode":"0452","adcode":"230221","name":"\u516d\u4e5d\u755c\u7267\u573a","level":"street","center_N":0,"center_J":0,"center_lng":122.896903,"center_lat":47.021364},{"citycode":"0452","adcode":"230221","name":"\u534e\u6c11\u826f\u79cd\u573a","level":"street","center_N":0,"center_J":0,"center_lng":123.440551,"center_lat":47.161375},{"citycode":"0452","adcode":"230221","name":"\u4e1c\u534e\u4e61","level":"street","center_N":0,"center_J":0,"center_lng":123.05804,"center_lat":46.788249},{"citycode":"0452","adcode":"230221","name":"\u9c81\u6cb3\u4e61","level":"street","center_N":0,"center_J":0,"center_lng":123.00586,"center_lat":47.44628},{"citycode":"0452","adcode":"230221","name":"\u767d\u5c71\u4e61","level":"street","center_N":0,"center_J":0,"center_lng":123.24997,"center_lat":47.269889}]