[{"citycode":"0591","adcode":"350111","name":"\u9f13\u5cad\u4e61","level":"street","center_N":0,"center_J":0,"center_lng":119.403236,"center_lat":26.085903},{"citycode":"0591","adcode":"350111","name":"\u5ba6\u6eaa\u9547","level":"street","center_N":0,"center_J":0,"center_lng":119.357478,"center_lat":26.173258},{"citycode":"0591","adcode":"350111","name":"\u5bff\u5c71\u4e61","level":"street","center_N":0,"center_J":0,"center_lng":119.278118,"center_lat":26.184549},{"citycode":"0591","adcode":"350111","name":"\u8c61\u56ed\u8857\u9053","level":"street","center_N":0,"center_J":0,"center_lng":119.328165,"center_lat":26.06653},{"citycode":"0591","adcode":"350111","name":"\u5cb3\u5cf0\u9547","level":"street","center_N":0,"center_J":0,"center_lng":119.32817,"center_lat":26.066532},{"citycode":"0591","adcode":"350111","name":"\u65b0\u5e97\u9547","level":"street","center_N":0,"center_J":0,"center_lng":119.311891,"center_lat":26.127483},{"citycode":"0591","adcode":"350111","name":"\u738b\u5e84\u8857\u9053","level":"street","center_N":0,"center_J":0,"center_lng":119.326339,"center_lat":26.079807},{"citycode":"0591","adcode":"350111","name":"\u8336\u56ed\u8857\u9053","level":"street","center_N":0,"center_J":0,"center_lng":119.319063,"center_lat":26.109753},{"citycode":"0591","adcode":"350111","name":"\u9f13\u5c71\u9547","level":"street","center_N":0,"center_J":0,"center_lng":119.353021,"center_lat":26.072075}]