[{"citycode":"0372","adcode":"410581","name":"\u8336\u5e97\u4e61","level":"street","center_N":0,"center_J":0,"center_lng":113.825124,"center_lat":35.830655},{"citycode":"0372","adcode":"410581","name":"\u77f3\u677f\u5ca9\u4e61","level":"street","center_N":0,"center_J":0,"center_lng":113.725834,"center_lat":36.165897},{"citycode":"0372","adcode":"410581","name":"\u57ce\u90ca\u4e61","level":"street","center_N":0,"center_J":0,"center_lng":113.819096,"center_lat":36.066596},{"citycode":"0372","adcode":"410581","name":"\u6842\u56ed\u8857\u9053","level":"street","center_N":0,"center_J":0,"center_lng":113.839835,"center_lat":36.075223},{"citycode":"0372","adcode":"410581","name":"\u4e34\u6dc7\u9547","level":"street","center_N":0,"center_J":0,"center_lng":113.89186,"center_lat":35.771423},{"citycode":"0372","adcode":"410581","name":"\u8336\u5e97\u9547","level":"street","center_N":0,"center_J":0,"center_lng":113.82526,"center_lat":35.830708},{"citycode":"0372","adcode":"410581","name":"\u4e1c\u59da\u9547","level":"street","center_N":0,"center_J":0,"center_lng":113.95849,"center_lat":35.91393},{"citycode":"0372","adcode":"410581","name":"\u4e94\u9f99\u9547","level":"street","center_N":0,"center_J":0,"center_lng":113.929939,"center_lat":35.762741},{"citycode":"0372","adcode":"410581","name":"\u59da\u6751\u9547","level":"street","center_N":0,"center_J":0,"center_lng":113.807879,"center_lat":36.178379},{"citycode":"0372","adcode":"410581","name":"\u74e6\u7a91\u8857\u9053","level":"street","center_N":0,"center_J":0,"center_lng":113.825145,"center_lat":36.06846},{"citycode":"0372","adcode":"410581","name":"\u4efb\u6751\u9547","level":"street","center_N":0,"center_J":0,"center_lng":113.813349,"center_lat":36.274821},{"citycode":"0372","adcode":"410581","name":"\u5408\u6da7\u9547","level":"street","center_N":0,"center_J":0,"center_lng":113.743629,"center_lat":35.970521},{"citycode":"0372","adcode":"410581","name":"\u9675\u9633\u9547","level":"street","center_N":0,"center_J":0,"center_lng":113.857904,"center_lat":36.124869},{"citycode":"0372","adcode":"410581","name":"\u6a2a\u6c34\u9547","level":"street","center_N":0,"center_J":0,"center_lng":113.922446,"center_lat":36.053766},{"citycode":"0372","adcode":"410581","name":"\u9f99\u5c71\u8857\u9053","level":"street","center_N":0,"center_J":0,"center_lng":113.83734,"center_lat":36.058029},{"citycode":"0372","adcode":"410581","name":"\u539f\u5eb7\u9547","level":"street","center_N":0,"center_J":0,"center_lng":113.756171,"center_lat":35.909874},{"citycode":"0372","adcode":"410581","name":"\u6842\u6797\u9547","level":"street","center_N":0,"center_J":0,"center_lng":113.82351,"center_lat":35.926855},{"citycode":"0372","adcode":"410581","name":"\u91c7\u6851\u9547","level":"street","center_N":0,"center_J":0,"center_lng":113.90666,"center_lat":35.99497},{"citycode":"0372","adcode":"410581","name":"\u5f00\u5143\u8857\u9053","level":"street","center_N":0,"center_J":0,"center_lng":113.818499,"center_lat":36.0681},{"citycode":"0372","adcode":"410581","name":"\u6cb3\u987a\u9547","level":"street","center_N":0,"center_J":0,"center_lng":113.927702,"center_lat":36.16095},{"citycode":"0372","adcode":"410581","name":"\u4e1c\u5c97\u9547","level":"street","center_N":0,"center_J":0,"center_lng":113.925022,"center_lat":36.256842}]