[{"citycode":"027","adcode":"420105","name":"\u6708\u6e56\u8857\u9053","level":"street","center_N":0,"center_J":0,"center_lng":114.255766,"center_lat":30.561294},{"citycode":"027","adcode":"420105","name":"\u6c5f\u5824\u8857\u9053","level":"street","center_N":0,"center_J":0,"center_lng":114.243014,"center_lat":30.518518},{"citycode":"027","adcode":"420105","name":"\u5468\u6e7e","level":"street","center_N":0,"center_J":0,"center_lng":114.179921,"center_lat":30.565116},{"citycode":"027","adcode":"420105","name":"\u90ed\u5bb6\u6e7e","level":"street","center_N":0,"center_J":0,"center_lng":114.1852,"center_lat":30.57403},{"citycode":"027","adcode":"420105","name":"\u6708\u6e56\u8857\u9053","level":"street","center_N":0,"center_J":0,"center_lng":114.244458,"center_lat":30.559611},{"citycode":"027","adcode":"420105","name":"\u6c5f\u6c49\u4e8c\u6865\u8857\u9053","level":"street","center_N":0,"center_J":0,"center_lng":114.210788,"center_lat":30.566986},{"citycode":"027","adcode":"420105","name":"\u5efa\u6865\u8857\u9053","level":"street","center_N":0,"center_J":0,"center_lng":114.273149,"center_lat":30.54778},{"citycode":"027","adcode":"420105","name":"\u7fe0\u5fae\u8857\u8857\u9053","level":"street","center_N":0,"center_J":0,"center_lng":114.263131,"center_lat":30.54604},{"citycode":"027","adcode":"420105","name":"\u7fe0\u5fae\u8857\u9053","level":"street","center_N":0,"center_J":0,"center_lng":114.263968,"center_lat":30.546133},{"citycode":"027","adcode":"420105","name":"\u6674\u5ddd\u8857\u9053","level":"street","center_N":0,"center_J":0,"center_lng":114.284347,"center_lat":30.5602},{"citycode":"027","adcode":"420105","name":"\u4e94\u91cc\u58a9\u8857\u9053","level":"street","center_N":0,"center_J":0,"center_lng":114.239022,"center_lat":30.553686},{"citycode":"027","adcode":"420105","name":"\u6d32\u5934\u8857\u9053","level":"street","center_N":0,"center_J":0,"center_lng":114.254841,"center_lat":30.523457},{"citycode":"027","adcode":"420105","name":"\u9e66\u9e49\u8857\u9053","level":"street","center_N":0,"center_J":0,"center_lng":114.269575,"center_lat":30.535582},{"citycode":"027","adcode":"420105","name":"\u6c38\u4e30\u8857\u9053","level":"street","center_N":0,"center_J":0,"center_lng":114.213989,"center_lat":30.564158},{"citycode":"027","adcode":"420105","name":"\u7434\u65ad\u53e3\u8857\u8857\u9053","level":"street","center_N":0,"center_J":0,"center_lng":114.21666,"center_lat":30.559041},{"citycode":"027","adcode":"420105","name":"\u7434\u65ad\u53e3\u8857\u9053","level":"street","center_N":0,"center_J":0,"center_lng":114.217075,"center_lat":30.558291}]