[{"citycode":"0745","adcode":"431227","name":"\u79be\u6ee9\u4e61","level":"street","center_N":0,"center_J":0,"center_lng":109.23257,"center_lat":27.279453},{"citycode":"0745","adcode":"431227","name":"\u664f\u5bb6\u4e61","level":"street","center_N":0,"center_J":0,"center_lng":109.1055,"center_lat":27.25045},{"citycode":"0745","adcode":"431227","name":"\u5927\u6e7e\u7f57\u4e61","level":"street","center_N":0,"center_J":0,"center_lng":109.174559,"center_lat":27.36776},{"citycode":"0745","adcode":"431227","name":"\u65b9\u5bb6\u5c6f\u4e61","level":"street","center_N":0,"center_J":0,"center_lng":109.170723,"center_lat":27.366663},{"citycode":"0745","adcode":"431227","name":"\u78a7\u6717\u4e61","level":"street","center_N":0,"center_J":0,"center_lng":109.35982,"center_lat":27.182851},{"citycode":"0745","adcode":"431227","name":"\u51f3\u5be8\u4e61","level":"street","center_N":0,"center_J":0,"center_lng":108.898844,"center_lat":27.036549},{"citycode":"0745","adcode":"431227","name":"\u674e\u6811\u4e61","level":"street","center_N":0,"center_J":0,"center_lng":109.176351,"center_lat":27.23313},{"citycode":"0745","adcode":"431227","name":"\u8336\u576a\u4e61","level":"street","center_N":0,"center_J":0,"center_lng":108.877131,"center_lat":27.077177},{"citycode":"0745","adcode":"431227","name":"\u7ecd\u6eaa\u5927\u961f\u6797\u573a","level":"street","center_N":0,"center_J":0,"center_lng":109.149826,"center_lat":27.124084},{"citycode":"0745","adcode":"431227","name":"\u51c9\u4f1e\u9547","level":"street","center_N":0,"center_J":0,"center_lng":108.95032,"center_lat":27.084666},{"citycode":"0745","adcode":"431227","name":"\u4e2d\u5be8\u9547","level":"street","center_N":0,"center_J":0,"center_lng":109.268139,"center_lat":27.195668},{"citycode":"0745","adcode":"431227","name":"\u6d1e\u576a\u4e61","level":"street","center_N":0,"center_J":0,"center_lng":109.30372,"center_lat":27.323236},{"citycode":"0745","adcode":"431227","name":"\u6276\u7f57\u9547","level":"street","center_N":0,"center_J":0,"center_lng":109.142149,"center_lat":27.187758},{"citycode":"0745","adcode":"431227","name":"\u65b0\u5be8\u4e61","level":"street","center_N":0,"center_J":0,"center_lng":109.065356,"center_lat":27.141524},{"citycode":"0745","adcode":"431227","name":"\u9c7c\u5e02\u9547","level":"street","center_N":0,"center_J":0,"center_lng":109.08309,"center_lat":27.32822},{"citycode":"0745","adcode":"431227","name":"\u524d\u8fdb\u5927\u961f\u6797\u573a","level":"street","center_N":0,"center_J":0,"center_lng":109.144744,"center_lat":27.152722},{"citycode":"0745","adcode":"431227","name":"\u65b0\u6643\u9547","level":"street","center_N":0,"center_J":0,"center_lng":109.174932,"center_lat":27.352681},{"citycode":"0745","adcode":"431227","name":"\u6ce2\u6d32\u9547","level":"street","center_N":0,"center_J":0,"center_lng":109.290853,"center_lat":27.378371},{"citycode":"0745","adcode":"431227","name":"\u6b65\u5934\u964d\u82d7\u65cf\u4e61","level":"street","center_N":0,"center_J":0,"center_lng":109.368735,"center_lat":27.295689},{"citycode":"0745","adcode":"431227","name":"\u5174\u9686\u9547","level":"street","center_N":0,"center_J":0,"center_lng":109.179786,"center_lat":27.347548},{"citycode":"0745","adcode":"431227","name":"\u5929\u5802\u4e61","level":"street","center_N":0,"center_J":0,"center_lng":109.00864,"center_lat":27.189951},{"citycode":"0745","adcode":"431227","name":"\u8d21\u6eaa\u4e61","level":"street","center_N":0,"center_J":0,"center_lng":109.16897,"center_lat":27.12165},{"citycode":"0745","adcode":"431227","name":"\u9ec4\u96f7\u4e61","level":"street","center_N":0,"center_J":0,"center_lng":108.94217,"center_lat":27.186861},{"citycode":"0745","adcode":"431227","name":"\u7c73\u8d1d\u82d7\u65cf\u4e61","level":"street","center_N":0,"center_J":0,"center_lng":109.380628,"center_lat":27.202164},{"citycode":"0745","adcode":"431227","name":"\u6797\u51b2\u4e61","level":"street","center_N":0,"center_J":0,"center_lng":109.024389,"center_lat":27.281937}]