[{"citycode":"023","adcode":"500101","name":"\u4f59\u5bb6\u9547","level":"street","center_N":0,"center_J":0,"center_lng":107.962104,"center_lat":30.801498},{"citycode":"023","adcode":"500101","name":"\u77f3\u9f99\u4e61","level":"street","center_N":0,"center_J":0,"center_lng":108.663573,"center_lat":30.836428},{"citycode":"023","adcode":"500101","name":"\u9ec4\u6ce5\u4e61","level":"street","center_N":0,"center_J":0,"center_lng":108.118459,"center_lat":30.682995},{"citycode":"023","adcode":"500101","name":"\u6eaa\u53e3\u4e61","level":"street","center_N":0,"center_J":0,"center_lng":108.343818,"center_lat":30.607403},{"citycode":"023","adcode":"500101","name":"\u53cc\u6d41\u4e61","level":"street","center_N":0,"center_J":0,"center_lng":108.483967,"center_lat":30.598323},{"citycode":"023","adcode":"500101","name":"\u674e\u6cb3\u9547","level":"street","center_N":0,"center_J":0,"center_lng":108.266139,"center_lat":30.815786},{"citycode":"023","adcode":"500101","name":"\u7518\u5b81\u9547","level":"street","center_N":0,"center_J":0,"center_lng":108.282265,"center_lat":30.668997},{"citycode":"023","adcode":"500101","name":"\u767d\u7f8a\u9547","level":"street","center_N":0,"center_J":0,"center_lng":108.616795,"center_lat":30.813663},{"citycode":"023","adcode":"500101","name":"\u592a\u767d\u5ca9\u8857\u9053","level":"street","center_N":0,"center_J":0,"center_lng":108.356664,"center_lat":30.817549},{"citycode":"023","adcode":"500101","name":"\u6787\u6777\u576a\u8857\u9053","level":"street","center_N":0,"center_J":0,"center_lng":108.402671,"center_lat":30.82955},{"citycode":"023","adcode":"500101","name":"\u53cc\u6cb3\u53e3\u8857\u9053","level":"street","center_N":0,"center_J":0,"center_lng":108.373857,"center_lat":30.748008},{"citycode":"023","adcode":"500101","name":"\u949f\u9f13\u697c\u8857\u9053","level":"street","center_N":0,"center_J":0,"center_lng":108.388801,"center_lat":30.823399},{"citycode":"023","adcode":"500101","name":"\u5927\u5174\u4e61","level":"street","center_N":0,"center_J":0,"center_lng":108.048124,"center_lat":30.642361},{"citycode":"023","adcode":"500101","name":"\u9f99\u6c99\u9547","level":"street","center_N":0,"center_J":0,"center_lng":108.237769,"center_lat":30.634316},{"citycode":"023","adcode":"500101","name":"\u54cd\u6c34\u9547","level":"street","center_N":0,"center_J":0,"center_lng":108.19774,"center_lat":30.653519},{"citycode":"023","adcode":"500101","name":"\u8d70\u9a6c\u9547","level":"street","center_N":0,"center_J":0,"center_lng":108.444361,"center_lat":30.566889},{"citycode":"023","adcode":"500101","name":"\u5f39\u5b50\u9547","level":"street","center_N":0,"center_J":0,"center_lng":108.010265,"center_lat":30.855069},{"citycode":"023","adcode":"500101","name":"\u5b59\u5bb6\u9547","level":"street","center_N":0,"center_J":0,"center_lng":108.01937,"center_lat":30.727359},{"citycode":"023","adcode":"500101","name":"\u5927\u7530\u4e61","level":"street","center_N":0,"center_J":0,"center_lng":108.559316,"center_lat":30.861892},{"citycode":"023","adcode":"500101","name":"\u53cc\u77f3\u4e61","level":"street","center_N":0,"center_J":0,"center_lng":108.604977,"center_lat":30.842998},{"citycode":"023","adcode":"500101","name":"\u9ad8\u5347\u9547","level":"street","center_N":0,"center_J":0,"center_lng":108.212382,"center_lat":30.792069},{"citycode":"023","adcode":"500101","name":"\u9ad8\u6881\u9547","level":"street","center_N":0,"center_J":0,"center_lng":108.305503,"center_lat":30.82439},{"citycode":"023","adcode":"500101","name":"\u8475\u82b1\u4e61","level":"street","center_N":0,"center_J":0,"center_lng":108.308392,"center_lat":30.805643},{"citycode":"023","adcode":"500101","name":"\u7f57\u7530\u9547","level":"street","center_N":0,"center_J":0,"center_lng":108.569413,"center_lat":30.516074},{"citycode":"023","adcode":"500101","name":"\u4e09\u6b63\u9547","level":"street","center_N":0,"center_J":0,"center_lng":108.162797,"center_lat":30.759322},{"citycode":"023","adcode":"500101","name":"\u9ad8\u7b0b\u5858\u8857\u9053","level":"street","center_N":0,"center_J":0,"center_lng":108.379923,"center_lat":30.800755},{"citycode":"023","adcode":"500101","name":"\u5927\u7891\u4e61","level":"street","center_N":0,"center_J":0,"center_lng":108.255137,"center_lat":30.860167},{"citycode":"023","adcode":"500101","name":"\u957f\u6ee9\u9547","level":"street","center_N":0,"center_J":0,"center_lng":108.609295,"center_lat":30.737812},{"citycode":"023","adcode":"500101","name":"\u56fd\u5bb6\u4e61","level":"street","center_N":0,"center_J":0,"center_lng":108.149383,"center_lat":30.653883},{"citycode":"023","adcode":"500101","name":"\u957f\u576a\u4e61","level":"street","center_N":0,"center_J":0,"center_lng":108.25428,"center_lat":30.442309},{"citycode":"023","adcode":"500101","name":"\u8328\u7af9\u4e61","level":"street","center_N":0,"center_J":0,"center_lng":108.51047,"center_lat":30.657488},{"citycode":"023","adcode":"500101","name":"\u666e\u5b50\u4e61","level":"street","center_N":0,"center_J":0,"center_lng":108.821633,"center_lat":30.567648},{"citycode":"023","adcode":"500101","name":"\u6865\u4ead\u4e61","level":"street","center_N":0,"center_J":0,"center_lng":108.090343,"center_lat":30.796418},{"citycode":"023","adcode":"500101","name":"\u5b59\u5bb6\u4e61","level":"street","center_N":0,"center_J":0,"center_lng":108.022932,"center_lat":30.725482},{"citycode":"023","adcode":"500101","name":"\u6cb9\u6c99\u4e61","level":"street","center_N":0,"center_J":0,"center_lng":108.474205,"center_lat":30.699132},{"citycode":"023","adcode":"500101","name":"\u56e2\u7ed3\u4e61","level":"street","center_N":0,"center_J":0,"center_lng":108.680228,"center_lat":30.674211},{"citycode":"023","adcode":"500101","name":"\u76d0\u4e95\u4e61","level":"street","center_N":0,"center_J":0,"center_lng":108.414323,"center_lat":30.594141},{"citycode":"023","adcode":"500101","name":"\u5206\u6c34\u9547","level":"street","center_N":0,"center_J":0,"center_lng":108.086862,"center_lat":30.717724},{"citycode":"023","adcode":"500101","name":"\u9f99\u5b9d\u9547","level":"street","center_N":0,"center_J":0,"center_lng":108.398508,"center_lat":30.760999},{"citycode":"023","adcode":"500101","name":"\u9648\u5bb6\u575d\u8857\u9053","level":"street","center_N":0,"center_J":0,"center_lng":108.413297,"center_lat":30.811712},{"citycode":"023","adcode":"500101","name":"\u592a\u5b89\u9547","level":"street","center_N":0,"center_J":0,"center_lng":108.654945,"center_lat":30.800876},{"citycode":"023","adcode":"500101","name":"\u9ad8\u5cf0\u9547","level":"street","center_N":0,"center_J":0,"center_lng":108.346585,"center_lat":30.70995},{"citycode":"023","adcode":"500101","name":"\u51c9\u98ce\u9547","level":"street","center_N":0,"center_J":0,"center_lng":108.286945,"center_lat":30.666194},{"citycode":"023","adcode":"500101","name":"\u67f1\u5c71\u4e61","level":"street","center_N":0,"center_J":0,"center_lng":108.27789,"center_lat":30.730131},{"citycode":"023","adcode":"500101","name":"\u6cb3\u53e3\u4e61","level":"street","center_N":0,"center_J":0,"center_lng":108.307684,"center_lat":30.639239},{"citycode":"023","adcode":"500101","name":"\u767d\u571f\u9547","level":"street","center_N":0,"center_J":0,"center_lng":108.815068,"center_lat":30.593909},{"citycode":"023","adcode":"500101","name":"\u9f99\u53e4\u4e61","level":"street","center_N":0,"center_J":0,"center_lng":108.217114,"center_lat":30.613509},{"citycode":"023","adcode":"500101","name":"\u5730\u5b9d\u4e61","level":"street","center_N":0,"center_J":0,"center_lng":108.899589,"center_lat":30.655356},{"citycode":"023","adcode":"500101","name":"\u5927\u6797\u4e61","level":"street","center_N":0,"center_J":0,"center_lng":108.852345,"center_lat":30.622854},{"citycode":"023","adcode":"500101","name":"\u6587\u660e\u4e61","level":"street","center_N":0,"center_J":0,"center_lng":108.684609,"center_lat":30.624898},{"citycode":"023","adcode":"500101","name":"\u90ed\u6751\u4e61","level":"street","center_N":0,"center_J":0,"center_lng":108.178261,"center_lat":30.558505},{"citycode":"023","adcode":"500101","name":"\u71d5\u5c71\u4e61","level":"street","center_N":0,"center_J":0,"center_lng":108.31199,"center_lat":30.551845},{"citycode":"023","adcode":"500101","name":"\u6c99\u6cb3\u8857\u9053","level":"street","center_N":0,"center_J":0,"center_lng":108.365493,"center_lat":30.848978},{"citycode":"023","adcode":"500101","name":"\u7ea2\u5149\u8857\u9053","level":"street","center_N":0,"center_J":0,"center_lng":108.357514,"center_lat":30.821345},{"citycode":"023","adcode":"500101","name":"\u718a\u5bb6\u9547","level":"street","center_N":0,"center_J":0,"center_lng":108.438181,"center_lat":30.89962},{"citycode":"023","adcode":"500101","name":"\u540e\u5c71\u9547","level":"street","center_N":0,"center_J":0,"center_lng":108.03628,"center_lat":30.82487},{"citycode":"023","adcode":"500101","name":"\u9e7f\u5c71\u4e61","level":"street","center_N":0,"center_J":0,"center_lng":108.322928,"center_lat":30.726886},{"citycode":"023","adcode":"500101","name":"\u4e09\u5143\u4e61","level":"street","center_N":0,"center_J":0,"center_lng":108.094193,"center_lat":30.624675},{"citycode":"023","adcode":"500101","name":"\u65b0\u4e61\u9547","level":"street","center_N":0,"center_J":0,"center_lng":108.2772,"center_lat":30.497821},{"citycode":"023","adcode":"500101","name":"\u703c\u6e21\u9547","level":"street","center_N":0,"center_J":0,"center_lng":108.310272,"center_lat":30.589596},{"citycode":"023","adcode":"500101","name":"\u6052\u5408\u571f\u5bb6\u65cf\u4e61","level":"street","center_N":0,"center_J":0,"center_lng":108.75962,"center_lat":30.529681},{"citycode":"023","adcode":"500101","name":"\u77f3\u4eba\u4e61","level":"street","center_N":0,"center_J":0,"center_lng":108.465623,"center_lat":30.805168},{"citycode":"023","adcode":"500101","name":"\u5927\u5468\u9547","level":"street","center_N":0,"center_J":0,"center_lng":108.502386,"center_lat":30.884865},{"citycode":"023","adcode":"500101","name":"\u68a8\u6811\u4e61","level":"street","center_N":0,"center_J":0,"center_lng":108.75163,"center_lat":30.662059},{"citycode":"023","adcode":"500101","name":"\u94c1\u5cf0\u4e61","level":"street","center_N":0,"center_J":0,"center_lng":108.403562,"center_lat":30.968887},{"citycode":"023","adcode":"500101","name":"\u592a\u767d\u5ca9\u8857\u9053","level":"street","center_N":0,"center_J":0,"center_lng":108.375962,"center_lat":30.818312},{"citycode":"023","adcode":"500101","name":"\u745e\u6c60\u4e61","level":"street","center_N":0,"center_J":0,"center_lng":108.161262,"center_lat":30.591281},{"citycode":"023","adcode":"500101","name":"\u4e2d\u5c71\u4e61","level":"street","center_N":0,"center_J":0,"center_lng":108.531294,"center_lat":30.530172},{"citycode":"023","adcode":"500101","name":"\u7518\u5b81\u4e61","level":"street","center_N":0,"center_J":0,"center_lng":108.25078,"center_lat":30.671594},{"citycode":"023","adcode":"500101","name":"\u5173\u9f99\u4e61","level":"street","center_N":0,"center_J":0,"center_lng":108.01614,"center_lat":30.769602},{"citycode":"023","adcode":"500101","name":"\u8305\u576a\u4e61","level":"street","center_N":0,"center_J":0,"center_lng":108.20288,"center_lat":30.777527},{"citycode":"023","adcode":"500101","name":"\u66fe\u5bb6\u4e61","level":"street","center_N":0,"center_J":0,"center_lng":108.749066,"center_lat":30.597755},{"citycode":"023","adcode":"500101","name":"\u94c1\u7089\u4e61","level":"street","center_N":0,"center_J":0,"center_lng":107.919229,"center_lat":30.785054},{"citycode":"023","adcode":"500101","name":"\u65b0\u8881\u4e61","level":"street","center_N":0,"center_J":0,"center_lng":108.074162,"center_lat":30.870773},{"citycode":"023","adcode":"500101","name":"\u5929\u57ce\u9547","level":"street","center_N":0,"center_J":0,"center_lng":108.37336,"center_lat":30.868549},{"citycode":"023","adcode":"500101","name":"\u9f99\u9a79\u9547","level":"street","center_N":0,"center_J":0,"center_lng":108.640749,"center_lat":30.60885},{"citycode":"023","adcode":"500101","name":"\u77f3\u6865\u4e61","level":"street","center_N":0,"center_J":0,"center_lng":108.251958,"center_lat":30.559962},{"citycode":"023","adcode":"500101","name":"\u5c0f\u5468\u9547","level":"street","center_N":0,"center_J":0,"center_lng":108.528086,"center_lat":30.919466},{"citycode":"023","adcode":"500101","name":"\u5ca9\u53e3\u4e61","level":"street","center_N":0,"center_J":0,"center_lng":108.293771,"center_lat":30.591389},{"citycode":"023","adcode":"500101","name":"\u90ed\u6751\u9547","level":"street","center_N":0,"center_J":0,"center_lng":108.17328,"center_lat":30.56387},{"citycode":"023","adcode":"500101","name":"\u724c\u697c\u8857\u9053","level":"street","center_N":0,"center_J":0,"center_lng":108.392121,"center_lat":30.783296},{"citycode":"023","adcode":"500101","name":"\u4e07\u5b89\u8857\u9053","level":"street","center_N":0,"center_J":0,"center_lng":108.386127,"center_lat":30.77543},{"citycode":"023","adcode":"500101","name":"\u9ec4\u67cf\u4e61","level":"street","center_N":0,"center_J":0,"center_lng":108.59762,"center_lat":30.915898},{"citycode":"023","adcode":"500101","name":"\u592a\u9f99\u9547","level":"street","center_N":0,"center_J":0,"center_lng":108.54008,"center_lat":30.902905},{"citycode":"023","adcode":"500101","name":"\u57f9\u6587\u9547","level":"street","center_N":0,"center_J":0,"center_lng":108.04645,"center_lat":30.596883},{"citycode":"023","adcode":"500101","name":"\u5c0f\u5cad\u4e61","level":"street","center_N":0,"center_J":0,"center_lng":108.432949,"center_lat":30.712037},{"citycode":"023","adcode":"500101","name":"\u5411\u5bb6\u4e61","level":"street","center_N":0,"center_J":0,"center_lng":108.72939,"center_lat":30.758872},{"citycode":"023","adcode":"500101","name":"\u4e5d\u6c60\u4e61","level":"street","center_N":0,"center_J":0,"center_lng":108.377817,"center_lat":30.788534},{"citycode":"023","adcode":"500101","name":"\u9e7f\u4e95\u4e61","level":"street","center_N":0,"center_J":0,"center_lng":108.205623,"center_lat":30.529782},{"citycode":"023","adcode":"500101","name":"\u5468\u5bb6\u575d\u8857\u9053","level":"street","center_N":0,"center_J":0,"center_lng":108.370388,"center_lat":30.846291},{"citycode":"023","adcode":"500101","name":"\u9f99\u90fd\u8857\u9053","level":"street","center_N":0,"center_J":0,"center_lng":108.411649,"center_lat":30.763107},{"citycode":"023","adcode":"500101","name":"\u767e\u5b89\u575d\u8857\u9053","level":"street","center_N":0,"center_J":0,"center_lng":108.449864,"center_lat":30.759836},{"citycode":"023","adcode":"500101","name":"\u4e94\u6865\u8857\u9053","level":"street","center_N":0,"center_J":0,"center_lng":108.448885,"center_lat":30.770818},{"citycode":"023","adcode":"500101","name":"\u65b0\u7530\u9547","level":"street","center_N":0,"center_J":0,"center_lng":108.406837,"center_lat":30.696436},{"citycode":"023","adcode":"500101","name":"\u957f\u5cad\u9547","level":"street","center_N":0,"center_J":0,"center_lng":108.489848,"center_lat":30.767762},{"citycode":"023","adcode":"500101","name":"\u6620\u6c34\u576a\u8857\u9053","level":"street","center_N":0,"center_J":0,"center_lng":108.369756,"center_lat":30.824099}]