[{"citycode":"0816","adcode":"510727","name":"\u6728\u5ea7\u85cf\u65cf\u4e61","level":"street","center_N":0,"center_J":0,"center_lng":104.5209,"center_lat":32.60636},{"citycode":"0816","adcode":"510727","name":"\u6c34\u89c2\u4e61","level":"street","center_N":0,"center_J":0,"center_lng":104.90993,"center_lat":32.2982},{"citycode":"0816","adcode":"510727","name":"\u5e73\u5357\u4e61","level":"street","center_N":0,"center_J":0,"center_lng":104.643608,"center_lat":32.173042},{"citycode":"0816","adcode":"510727","name":"\u53e4\u57ce\u9547","level":"street","center_N":0,"center_J":0,"center_lng":104.634735,"center_lat":32.377521},{"citycode":"0816","adcode":"510727","name":"\u9501\u6c5f\u7f8c\u65cf\u4e61","level":"street","center_N":0,"center_J":0,"center_lng":104.473123,"center_lat":32.163334},{"citycode":"0816","adcode":"510727","name":"\u767d\u9a6c\u85cf\u65cf\u4e61","level":"street","center_N":0,"center_J":0,"center_lng":104.322707,"center_lat":32.738665},{"citycode":"0816","adcode":"510727","name":"\u864e\u7259\u85cf\u65cf\u4e61","level":"street","center_N":0,"center_J":0,"center_lng":104.068261,"center_lat":32.5243},{"citycode":"0816","adcode":"510727","name":"\u5927\u6865\u9547","level":"street","center_N":0,"center_J":0,"center_lng":104.340465,"center_lat":32.376509},{"citycode":"0816","adcode":"510727","name":"\u6c34\u7530\u4e61","level":"street","center_N":0,"center_J":0,"center_lng":104.605055,"center_lat":32.320558},{"citycode":"0816","adcode":"510727","name":"\u6728\u76ae\u85cf\u65cf\u4e61","level":"street","center_N":0,"center_J":0,"center_lng":104.552597,"center_lat":32.535626},{"citycode":"0816","adcode":"510727","name":"\u6c34\u7530\u7f8c\u65cf\u4e61","level":"street","center_N":0,"center_J":0,"center_lng":104.607752,"center_lat":32.320585},{"citycode":"0816","adcode":"510727","name":"\u571f\u57ce\u4e61","level":"street","center_N":0,"center_J":0,"center_lng":104.217091,"center_lat":32.424989},{"citycode":"0816","adcode":"510727","name":"\u6cd7\u8033\u85cf\u65cf\u4e61","level":"street","center_N":0,"center_J":0,"center_lng":104.115311,"center_lat":32.230992},{"citycode":"0816","adcode":"510727","name":"\u5357\u575d\u9547","level":"street","center_N":0,"center_J":0,"center_lng":104.835677,"center_lat":32.200195},{"citycode":"0816","adcode":"510727","name":"\u5f90\u5858\u7f8c\u65cf\u4e61","level":"street","center_N":0,"center_J":0,"center_lng":104.49655,"center_lat":32.29686},{"citycode":"0816","adcode":"510727","name":"\u5f90\u5858\u4e61","level":"street","center_N":0,"center_J":0,"center_lng":104.500096,"center_lat":32.294187},{"citycode":"0816","adcode":"510727","name":"\u9614\u8fbe\u4e61","level":"street","center_N":0,"center_J":0,"center_lng":104.403737,"center_lat":32.465629},{"citycode":"0816","adcode":"510727","name":"\u9ad8\u6751\u4e61","level":"street","center_N":0,"center_J":0,"center_lng":104.70926,"center_lat":32.409839},{"citycode":"0816","adcode":"510727","name":"\u9614\u8fbe\u85cf\u65cf\u4e61","level":"street","center_N":0,"center_J":0,"center_lng":104.405762,"center_lat":32.468029},{"citycode":"0816","adcode":"510727","name":"\u8c46\u53e9\u9547","level":"street","center_N":0,"center_J":0,"center_lng":104.593181,"center_lat":32.104829},{"citycode":"0816","adcode":"510727","name":"\u9501\u6c5f\u4e61","level":"street","center_N":0,"center_J":0,"center_lng":104.472985,"center_lat":32.163272},{"citycode":"0816","adcode":"510727","name":"\u9ec4\u7f8a\u5173\u85cf\u65cf\u4e61","level":"street","center_N":0,"center_J":0,"center_lng":104.226053,"center_lat":32.544587},{"citycode":"0816","adcode":"510727","name":"\u65e7\u5821\u4e61","level":"street","center_N":0,"center_J":0,"center_lng":104.395888,"center_lat":32.362756},{"citycode":"0816","adcode":"510727","name":"\u5e73\u901a\u9547","level":"street","center_N":0,"center_J":0,"center_lng":104.691229,"center_lat":32.059867},{"citycode":"0816","adcode":"510727","name":"\u65e7\u5821\u7f8c\u65cf\u4e61","level":"street","center_N":0,"center_J":0,"center_lng":104.394577,"center_lat":32.366798},{"citycode":"0816","adcode":"510727","name":"\u9f99\u5b89\u9547","level":"street","center_N":0,"center_J":0,"center_lng":104.529069,"center_lat":32.408661},{"citycode":"0816","adcode":"510727","name":"\u575d\u5b50\u4e61","level":"street","center_N":0,"center_J":0,"center_lng":104.764338,"center_lat":32.284797},{"citycode":"0816","adcode":"510727","name":"\u54cd\u5ca9\u9547","level":"street","center_N":0,"center_J":0,"center_lng":104.772737,"center_lat":32.092925},{"citycode":"0816","adcode":"510727","name":"\u5927\u5370\u9547","level":"street","center_N":0,"center_J":0,"center_lng":104.525468,"center_lat":32.14186},{"citycode":"0816","adcode":"510727","name":"\u571f\u57ce\u85cf\u65cf\u4e61","level":"street","center_N":0,"center_J":0,"center_lng":104.217208,"center_lat":32.425416},{"citycode":"0816","adcode":"510727","name":"\u6c34\u6676\u9547","level":"street","center_N":0,"center_J":0,"center_lng":104.23394,"center_lat":32.490769},{"citycode":"0816","adcode":"510727","name":"\u5e73\u5357\u7f8c\u65cf\u4e61","level":"street","center_N":0,"center_J":0,"center_lng":104.63902,"center_lat":32.17593}]