[{"citycode":"0934","adcode":"621026","name":"\u592a\u660c\u4e61","level":"street","center_N":0,"center_J":0,"center_lng":107.778804,"center_lat":35.39982},{"citycode":"0934","adcode":"621026","name":"\u7c73\u6865\u4e61","level":"street","center_N":0,"center_J":0,"center_lng":108.29959,"center_lat":35.498788},{"citycode":"0934","adcode":"621026","name":"\u76d8\u514b\u9547","level":"street","center_N":0,"center_J":0,"center_lng":108.24923,"center_lat":35.746968},{"citycode":"0934","adcode":"621026","name":"\u5773\u9a6c\u4e61","level":"street","center_N":0,"center_J":0,"center_lng":107.845727,"center_lat":35.479871},{"citycode":"0934","adcode":"621026","name":"\u65b0\u5e84\u9547","level":"street","center_N":0,"center_J":0,"center_lng":107.819425,"center_lat":35.340983},{"citycode":"0934","adcode":"621026","name":"\u74e6\u659c\u4e61","level":"street","center_N":0,"center_J":0,"center_lng":107.889402,"center_lat":35.625618},{"citycode":"0934","adcode":"621026","name":"\u653f\u5e73\u4e61","level":"street","center_N":0,"center_J":0,"center_lng":107.948052,"center_lat":35.304302},{"citycode":"0934","adcode":"621026","name":"\u5e73\u5b50\u9547","level":"street","center_N":0,"center_J":0,"center_lng":108.186611,"center_lat":35.450268},{"citycode":"0934","adcode":"621026","name":"\u4e2d\u6751\u4e61","level":"street","center_N":0,"center_J":0,"center_lng":107.982438,"center_lat":35.360381},{"citycode":"0934","adcode":"621026","name":"\u5357\u4e49\u4e61","level":"street","center_N":0,"center_J":0,"center_lng":107.965906,"center_lat":35.628819},{"citycode":"0934","adcode":"621026","name":"\u826f\u5e73\u4e61","level":"street","center_N":0,"center_J":0,"center_lng":108.09158,"center_lat":35.443479},{"citycode":"0934","adcode":"621026","name":"\u4e2d\u6751\u9547","level":"street","center_N":0,"center_J":0,"center_lng":107.988634,"center_lat":35.359956},{"citycode":"0934","adcode":"621026","name":"\u6625\u8363\u9547","level":"street","center_N":0,"center_J":0,"center_lng":108.04354,"center_lat":35.531311},{"citycode":"0934","adcode":"621026","name":"\u6e58\u4e50\u9547","level":"street","center_N":0,"center_J":0,"center_lng":108.14889,"center_lat":35.59488},{"citycode":"0934","adcode":"621026","name":"\u77f3\u9f13\u4e61","level":"street","center_N":0,"center_J":0,"center_lng":108.13576,"center_lat":35.544537},{"citycode":"0934","adcode":"621026","name":"\u65e9\u80dc\u9547","level":"street","center_N":0,"center_J":0,"center_lng":108.006028,"center_lat":35.404301},{"citycode":"0934","adcode":"621026","name":"\u65b0\u5b81\u9547","level":"street","center_N":0,"center_J":0,"center_lng":107.926365,"center_lat":35.498308},{"citycode":"0934","adcode":"621026","name":"\u7126\u6751\u4e61","level":"street","center_N":0,"center_J":0,"center_lng":107.792539,"center_lat":35.518805},{"citycode":"0934","adcode":"621026","name":"\u7126\u6751\u9547","level":"street","center_N":0,"center_J":0,"center_lng":107.79433,"center_lat":35.518954},{"citycode":"0934","adcode":"621026","name":"\u65b0\u534e\u4e61","level":"street","center_N":0,"center_J":0,"center_lng":107.89382,"center_lat":35.293729},{"citycode":"0934","adcode":"621026","name":"\u548c\u76db\u9547","level":"street","center_N":0,"center_J":0,"center_lng":107.763662,"center_lat":35.446456},{"citycode":"0934","adcode":"621026","name":"\u91d1\u6751\u4e61","level":"street","center_N":0,"center_J":0,"center_lng":108.30064,"center_lat":35.65101},{"citycode":"0934","adcode":"621026","name":"\u957f\u5e86\u6865\u9547","level":"street","center_N":0,"center_J":0,"center_lng":107.75023,"center_lat":35.32264},{"citycode":"0934","adcode":"621026","name":"\u89c2\u97f3\u4e61","level":"street","center_N":0,"center_J":0,"center_lng":108.208299,"center_lat":35.707124},{"citycode":"0934","adcode":"621026","name":"\u4e5d\u5c98\u4e61","level":"street","center_N":0,"center_J":0,"center_lng":108.374687,"center_lat":35.6083},{"citycode":"0934","adcode":"621026","name":"\u6625\u8363\u4e61","level":"street","center_N":0,"center_J":0,"center_lng":108.042919,"center_lat":35.53176}]