[{"citycode":"0563","adcode":"341825","name":"\u4e91\u4e50\u4e61","level":"street","center_N":0,"center_J":0,"center_lng":118.638821,"center_lat":30.445347},{"citycode":"0563","adcode":"341825","name":"\u65cc\u9633\u9547","level":"street","center_N":0,"center_J":0,"center_lng":118.538933,"center_lat":30.286876},{"citycode":"0563","adcode":"341825","name":"\u767d\u5730\u9547","level":"street","center_N":0,"center_J":0,"center_lng":118.37666,"center_lat":30.201715},{"citycode":"0563","adcode":"341825","name":"\u4e09\u6eaa\u9547","level":"street","center_N":0,"center_J":0,"center_lng":118.433451,"center_lat":30.374468},{"citycode":"0563","adcode":"341825","name":"\u7248\u4e66\u4e61","level":"street","center_N":0,"center_J":0,"center_lng":118.511306,"center_lat":30.224471},{"citycode":"0563","adcode":"341825","name":"\u5b59\u6751\u4e61","level":"street","center_N":0,"center_J":0,"center_lng":118.419593,"center_lat":30.313275},{"citycode":"0563","adcode":"341825","name":"\u4fde\u6751\u4e61","level":"street","center_N":0,"center_J":0,"center_lng":118.634153,"center_lat":30.344545},{"citycode":"0563","adcode":"341825","name":"\u5174\u9686\u4e61","level":"street","center_N":0,"center_J":0,"center_lng":118.350435,"center_lat":30.351449},{"citycode":"0563","adcode":"341825","name":"\u8521\u5bb6\u6865\u9547","level":"street","center_N":0,"center_J":0,"center_lng":118.478697,"center_lat":30.341552},{"citycode":"0563","adcode":"341825","name":"\u5e99\u9996\u9547","level":"street","center_N":0,"center_J":0,"center_lng":118.400604,"center_lat":30.266868},{"citycode":"0563","adcode":"341825","name":"\u4ed5\u5ddd\u4e61","level":"street","center_N":0,"center_J":0,"center_lng":118.682795,"center_lat":30.288169},{"citycode":"0563","adcode":"341825","name":"\u4fde\u6751\u9547","level":"street","center_N":0,"center_J":0,"center_lng":118.634141,"center_lat":30.344975}]