[{"citycode":"0591","adcode":"350105","name":"\u4ead\u6c5f\u9547","level":"street","center_N":0,"center_J":0,"center_lng":119.516337,"center_lat":26.073567},{"citycode":"0591","adcode":"350105","name":"\u9a6c\u5c3e\u9547","level":"street","center_N":0,"center_J":0,"center_lng":119.428164,"center_lat":26.020579},{"citycode":"0591","adcode":"350105","name":"\u7f57\u661f\u8857\u9053","level":"street","center_N":0,"center_J":0,"center_lng":119.448989,"center_lat":25.982311},{"citycode":"0591","adcode":"350105","name":"\u7405\u5c90\u9547","level":"street","center_N":0,"center_J":0,"center_lng":119.583599,"center_lat":26.08539}]