[{"citycode":"0762","adcode":"441602","name":"\u6e90\u5357\u9547","level":"street","center_N":0,"center_J":0,"center_lng":114.689684,"center_lat":23.744132},{"citycode":"0762","adcode":"441602","name":"\u57d4\u524d\u9547","level":"street","center_N":0,"center_J":0,"center_lng":114.615147,"center_lat":23.569599},{"citycode":"0762","adcode":"441602","name":"\u4e1c\u57d4\u8857\u9053","level":"street","center_N":0,"center_J":0,"center_lng":114.709154,"center_lat":23.753827},{"citycode":"0762","adcode":"441602","name":"\u4e0a\u57ce\u8857\u9053","level":"street","center_N":0,"center_J":0,"center_lng":114.697348,"center_lat":23.736062},{"citycode":"0762","adcode":"441602","name":"\u6e90\u897f\u8857\u9053","level":"street","center_N":0,"center_J":0,"center_lng":114.683152,"center_lat":23.749751},{"citycode":"0762","adcode":"441602","name":"\u65b0\u6c5f\u8857\u9053","level":"street","center_N":0,"center_J":0,"center_lng":114.691314,"center_lat":23.736494},{"citycode":"0762","adcode":"441602","name":"\u9ad8\u57d4\u5c97\u8857\u9053","level":"street","center_N":0,"center_J":0,"center_lng":114.634592,"center_lat":23.616873}]