[{"citycode":"0854","adcode":"522702","name":"\u57ce\u53a2\u9547","level":"street","center_N":0,"center_J":0,"center_lng":107.510362,"center_lat":26.702993},{"citycode":"0854","adcode":"522702","name":"\u9646\u576a\u9547","level":"street","center_N":0,"center_J":0,"center_lng":107.64621,"center_lat":26.75584},{"citycode":"0854","adcode":"522702","name":"\u725b\u573a\u9547","level":"street","center_N":0,"center_J":0,"center_lng":107.454546,"center_lat":26.882111},{"citycode":"0854","adcode":"522702","name":"\u9ec4\u4e1d\u9547","level":"street","center_N":0,"center_J":0,"center_lng":107.409148,"center_lat":26.584455},{"citycode":"0854","adcode":"522702","name":"\u9ad8\u576a\u9547","level":"street","center_N":0,"center_J":0,"center_lng":107.361958,"center_lat":26.909907},{"citycode":"0854","adcode":"522702","name":"\u85dc\u5c71\u4e61","level":"street","center_N":0,"center_J":0,"center_lng":107.605453,"center_lat":26.711977},{"citycode":"0854","adcode":"522702","name":"\u5c94\u6cb3\u4e61","level":"street","center_N":0,"center_J":0,"center_lng":107.418967,"center_lat":26.693192},{"citycode":"0854","adcode":"522702","name":"\u5730\u677e\u9547","level":"street","center_N":0,"center_J":0,"center_lng":107.57521,"center_lat":26.79815},{"citycode":"0854","adcode":"522702","name":"\u9053\u576a\u9547","level":"street","center_N":0,"center_J":0,"center_lng":107.33634,"center_lat":26.92729},{"citycode":"0854","adcode":"522702","name":"\u51e4\u5c71\u9547","level":"street","center_N":0,"center_J":0,"center_lng":107.632195,"center_lat":26.634303},{"citycode":"0854","adcode":"522702","name":"\u9f99\u660c\u9547","level":"street","center_N":0,"center_J":0,"center_lng":107.463982,"center_lat":26.773532},{"citycode":"0854","adcode":"522702","name":"\u4ed9\u6865\u4e61","level":"street","center_N":0,"center_J":0,"center_lng":107.300214,"center_lat":26.754576},{"citycode":"0854","adcode":"522702","name":"\u5174\u9686\u4e61","level":"street","center_N":0,"center_J":0,"center_lng":107.697223,"center_lat":26.617504}]