[{"citycode":"0876","adcode":"532626","name":"\u5b98\u5be8\u4e61","level":"street","center_N":0,"center_J":0,"center_lng":104.045934,"center_lat":24.296666},{"citycode":"0876","adcode":"532626","name":"\u53cc\u9f99\u8425\u9547","level":"street","center_N":0,"center_J":0,"center_lng":104.199814,"center_lat":24.196539},{"citycode":"0876","adcode":"532626","name":"\u65e5\u8005\u4e61","level":"street","center_N":0,"center_J":0,"center_lng":104.010758,"center_lat":24.16562},{"citycode":"0876","adcode":"532626","name":"\u6811\u76ae\u5f5d\u65cf\u4e61","level":"street","center_N":0,"center_J":0,"center_lng":104.104288,"center_lat":23.879551},{"citycode":"0876","adcode":"532626","name":"\u5929\u661f\u4e61","level":"street","center_N":0,"center_J":0,"center_lng":104.305094,"center_lat":23.939586},{"citycode":"0876","adcode":"532626","name":"\u65b0\u5e97\u5f5d\u65cf\u4e61","level":"street","center_N":0,"center_J":0,"center_lng":103.732342,"center_lat":24.025113},{"citycode":"0876","adcode":"532626","name":"\u820d\u5f97\u4e61","level":"street","center_N":0,"center_J":0,"center_lng":103.868288,"center_lat":24.234984},{"citycode":"0876","adcode":"532626","name":"\u7f8a\u8857\u4e61","level":"street","center_N":0,"center_J":0,"center_lng":104.47619,"center_lat":24.32966},{"citycode":"0876","adcode":"532626","name":"\u817b\u811a\u5f5d\u65cf\u4e61","level":"street","center_N":0,"center_J":0,"center_lng":103.851241,"center_lat":24.039702},{"citycode":"0876","adcode":"532626","name":"\u5e73\u5be8\u4e61","level":"street","center_N":0,"center_J":0,"center_lng":104.368962,"center_lat":24.053592},{"citycode":"0876","adcode":"532626","name":"\u516b\u9053\u54e8\u5f5d\u65cf\u4e61","level":"street","center_N":0,"center_J":0,"center_lng":104.087413,"center_lat":24.097461},{"citycode":"0876","adcode":"532626","name":"\u6e29\u6d4f\u4e61","level":"street","center_N":0,"center_J":0,"center_lng":104.423568,"center_lat":24.282776},{"citycode":"0876","adcode":"532626","name":"\u66f0\u8005\u9547","level":"street","center_N":0,"center_J":0,"center_lng":104.008368,"center_lat":24.164361},{"citycode":"0876","adcode":"532626","name":"\u820d\u5f97\u5f5d\u65cf\u4e61","level":"street","center_N":0,"center_J":0,"center_lng":103.868271,"center_lat":24.234991},{"citycode":"0876","adcode":"532626","name":"\u9526\u5c4f\u9547","level":"street","center_N":0,"center_J":0,"center_lng":104.195621,"center_lat":24.042368},{"citycode":"0876","adcode":"532626","name":"\u677f\u6865\u519c\u573a","level":"street","center_N":0,"center_J":0,"center_lng":104.092327,"center_lat":24.16934},{"citycode":"0876","adcode":"532626","name":"\u83b2\u82b1\u5858\u519c\u573a","level":"street","center_N":0,"center_J":0,"center_lng":104.039435,"center_lat":24.172322}]